{"card_name": "Scarletblood Hound", "color": "R", "rarity": "cube", "type": "Creature \u2013 Hound", "number": 200, "color_identity": "R", "cost": "{2}{R}", "rules_text": "Haste\n[i]Motley[/i] \u2013 At the beginning of your upkeep, if there are five or more names among nonland permanents you control, Scarletblood Hound deals 3 damage to each opponent.", "flavor_text": "[i][/i]", "pt": "3/1", "special_text": "", "shape": "normal", "set": "MC25", "loyalty": "", "artist": "wood-illustration", "notes": "", "image_type": "png"}