{"card_name": "Herald of the White Orchid", "color": "W", "rarity": "cube", "type": "Creature \u2013 Human Soldier", "number": 33, "color_identity": "W", "cost": "{W}", "rules_text": "Encourage [i]({T}: Another target creature you control gets +1/+1 until end of turn. Encourage only as a sorcery.)[/i]\nWhenever a creature deals combat damage to a player, if it was encouraged by Herald of the White Orchid this turn, create a 1/1 white Soldier creature token.", "flavor_text": "[i][/i]", "pt": "1/1", "special_text": "", "shape": "normal", "set": "MC25", "loyalty": "", "artist": "Indigo Jenar", "notes": "", "image_type": "png"}