{"card_name": "Retort Nonsense", "color": "U", "rarity": "cube", "type": "Instant", "number": 94, "color_identity": "U", "cost": "{1}{U}{U}", "rules_text": "Counter target spell.\nYou may draw four cards. If you do, skip your next turn.", "flavor_text": "[i]\u201cThe problem with driving your library guards mad is that sometimes, the random words they string together form powerful spells by accident.\u201d\n\u2014Witch-Queen Yarag[/i]", "pt": "", "special_text": "", "shape": "normal", "set": "MC25", "loyalty": "", "artist": "FlerPainter", "notes": "!FT: fluffyDeathbringer2", "image_type": "png"}