{"card_name": "Artificial Sanctity", "color": "W", "rarity": "cube", "type": "Enchantment", "number": 9, "color_identity": "W", "cost": "{4}{W}", "rules_text": "Creatures you control get +2/+2.\nLifecycle {3} [i]({3}, Discard this card: Create two tapped 1/1 colorless Elemental creature tokens.)[/i]", "flavor_text": "[i]The chamber rings with hymns muttered out of compliance, not reverence.[/i]", "pt": "", "special_text": "", "shape": "normal", "set": "MC25", "loyalty": "", "artist": "Emanuel Dias", "notes": "!FT: Mako", "image_type": "png"}