{"card_name": "Azamir, Wayward Titan", "color": "", "rarity": "cube", "type": "Legendary Planeswalker \u2013 Azamir", "number": 1, "color_identity": "C", "cost": "{8}", "rules_text": "", "flavor_text": "[i][/i]", "pt": "", "special_text": "You may play cards exiled with Azamir planeswalkers.\n[+2]: Search each player's library for a card and exile it. Shuffle each library searched this way.\n[-3]: Each opponent chooses a permanent they control for each permanent type, then exiles those permanents.\n[-8]: Exile all cards your opponents own from outside the game. Until end of turn, you may cast spells without paying their mana costs and you may play cards exiled with Azamir planeswalkers.", "shape": "planeswalker", "set": "VOA", "loyalty": "5", "artist": "Paolo Puggioni", "notes": "", "image_type": "png"}